modelgauge/annotators/demo_annotator.py
modelgauge/suts/demo_01_yes_no_sut.py
modelgauge/suts/demo_02_secrets_and_options_sut.py
modelgauge/suts/demo_03_sut_with_args.py
modelgauge/tests/demo_01_simple_qa_test.py
modelgauge/tests/demo_02_unpacking_dependency_test.py
modelgauge/tests/demo_03_paired_prompts_test.py
modelgauge/tests/demo_04_using_annotation_test.py
modelgauge/tests/specifications/README.md
modelgauge/tests/specifications/demo_01.toml
modelgauge_demo_plugin-0.6.3.dist-info/METADATA
modelgauge_demo_plugin-0.6.3.dist-info/WHEEL
modelgauge_demo_plugin-0.6.3.dist-info/RECORD
